odoo/addons/ssi_lead_risk_analysis/README.rst
odoo/addons/ssi_lead_risk_analysis/__init__.py
odoo/addons/ssi_lead_risk_analysis/__manifest__.py
odoo/addons/ssi_lead_risk_analysis/i18n/ssi_lead_risk_analysis.pot
odoo/addons/ssi_lead_risk_analysis/models/__init__.py
odoo/addons/ssi_lead_risk_analysis/models/crm_lead.py
odoo/addons/ssi_lead_risk_analysis/static/description/icon.png
odoo/addons/ssi_lead_risk_analysis/views/crm_lead_views.xml
odoo14_addon_ssi_lead_risk_analysis-14.0.1.1.0.dist-info/METADATA
odoo14_addon_ssi_lead_risk_analysis-14.0.1.1.0.dist-info/WHEEL
odoo14_addon_ssi_lead_risk_analysis-14.0.1.1.0.dist-info/top_level.txt
odoo14_addon_ssi_lead_risk_analysis-14.0.1.1.0.dist-info/RECORD
